Metadata-Version: 1.0
Name: ftpbackup
Version: 0.1.5
Summary: Backup the folder to FTP!
Home-page: https://github.com/mickey9910326/ftpbackup
Author: mickey9910326
Author-email: mickey9910326@gmail.com
License: MIT
Platform: UNKNOWN
